[{"id":"20191122","route":{"id":"get-started_details","path":"/get-started/details"},"needsManualCheck":false,"violations":[{"id":"aria-input-field-name","impact":"serious","tags":["wcag2a","wcag412"],"description":"Ensures every ARIA input field has an accessible name","help":"ARIA input fields have an accessible name","helpUrl":"https://dequeuniversity.com/rules/axe/3.3/aria-input-field-name?application=axe-puppeteer","nodes":[{"any":[{"id":"aria-label","data":null,"relatedNodes":[],"impact":"serious","message":"aria-label attribute does not exist or is empty"},{"id":"aria-labelledby","data":null,"relatedNodes":[],"impact":"serious","message":"aria-labelledby attribute does not exist, references elements that do not exist or references elements that are empty"},{"id":"non-empty-title","data":null,"relatedNodes":[],"impact":"serious","message":"Element has no title attribute or the title attribute is empty"}],"all":[],"none":[],"impact":"serious","html":"<div tabindex=\"0\" class=\"SomethingElse_main__16if9\" data-testid=\"something-else\" role=\"combobox\" aria-expanded=\"false\" aria-haspopup=\"listbox\" aria-labelledby=\"downshift-0-label\">","target":["div[aria-labelledby=\"downshift-0-label\"]"],"failureSummary":"Fix any of the following:\n  aria-label attribute does not exist or is empty\n  aria-labelledby attribute does not exist, references elements that do not exist or references elements that are empty\n  Element has no title attribute or the title attribute is empty"},{"any":[{"id":"aria-label","data":null,"relatedNodes":[],"impact":"serious","message":"aria-label attribute does not exist or is empty"},{"id":"aria-labelledby","data":null,"relatedNodes":[],"impact":"serious","message":"aria-labelledby attribute does not exist, references elements that do not exist or references elements that are empty"},{"id":"non-empty-title","data":null,"relatedNodes":[],"impact":"serious","message":"Element has no title attribute or the title attribute is empty"}],"all":[],"none":[],"impact":"serious","html":"<div tabindex=\"0\" class=\"SomethingElse_main__16if9\" data-testid=\"something-else\" role=\"combobox\" aria-expanded=\"false\" aria-haspopup=\"listbox\" aria-labelledby=\"downshift-1-label\">","target":["div[aria-labelledby=\"downshift-1-label\"]"],"failureSummary":"Fix any of the following:\n  aria-label attribute does not exist or is empty\n  aria-labelledby attribute does not exist, references elements that do not exist or references elements that are empty\n  Element has no title attribute or the title attribute is empty"}]},{"id":"aria-required-children","impact":"critical","tags":["cat.aria","wcag2a","wcag131"],"description":"Ensures elements with an ARIA role that require child roles contain them","help":"Certain ARIA roles must contain particular children","helpUrl":"https://dequeuniversity.com/rules/axe/3.3/aria-required-children?application=axe-puppeteer","nodes":[{"any":[{"id":"aria-required-children","data":["textbox"],"relatedNodes":[],"impact":"critical","message":"Required ARIA child role not present: textbox"}],"all":[],"none":[],"impact":"critical","html":"<div tabindex=\"0\" class=\"SomethingElse_main__16if9\" data-testid=\"something-else\" role=\"combobox\" aria-expanded=\"false\" aria-haspopup=\"listbox\" aria-labelledby=\"downshift-0-label\">","target":["div[aria-labelledby=\"downshift-0-label\"]"],"failureSummary":"Fix any of the following:\n  Required ARIA child role not present: textbox"},{"any":[{"id":"aria-required-children","data":["textbox"],"relatedNodes":[],"impact":"critical","message":"Required ARIA child role not present: textbox"}],"all":[],"none":[],"impact":"critical","html":"<div tabindex=\"0\" class=\"SomethingElse_main__16if9\" data-testid=\"something-else\" role=\"combobox\" aria-expanded=\"false\" aria-haspopup=\"listbox\" aria-labelledby=\"downshift-1-label\">","target":["div[aria-labelledby=\"downshift-1-label\"]"],"failureSummary":"Fix any of the following:\n  Required ARIA child role not present: textbox"}]},{"id":"aria-valid-attr-value","impact":"critical","tags":["cat.aria","wcag2a","wcag412"],"description":"Ensures all ARIA attributes have valid values","help":"ARIA attributes must conform to valid values","helpUrl":"https://dequeuniversity.com/rules/axe/3.3/aria-valid-attr-value?application=axe-puppeteer","nodes":[{"any":[],"all":[{"id":"aria-valid-attr-value","data":["aria-labelledby=\"downshift-0-label\""],"relatedNodes":[],"impact":"critical","message":"Invalid ARIA attribute value: aria-labelledby=\"downshift-0-label\""}],"none":[],"impact":"critical","html":"<div tabindex=\"0\" class=\"SomethingElse_main__16if9\" data-testid=\"something-else\" role=\"combobox\" aria-expanded=\"false\" aria-haspopup=\"listbox\" aria-labelledby=\"downshift-0-label\">","target":["div[aria-labelledby=\"downshift-0-label\"]"],"failureSummary":"Fix all of the following:\n  Invalid ARIA attribute value: aria-labelledby=\"downshift-0-label\""},{"any":[],"all":[{"id":"aria-valid-attr-value","data":["aria-labelledby=\"downshift-1-label\""],"relatedNodes":[],"impact":"critical","message":"Invalid ARIA attribute value: aria-labelledby=\"downshift-1-label\""}],"none":[],"impact":"critical","html":"<div tabindex=\"0\" class=\"SomethingElse_main__16if9\" data-testid=\"something-else\" role=\"combobox\" aria-expanded=\"false\" aria-haspopup=\"listbox\" aria-labelledby=\"downshift-1-label\">","target":["div[aria-labelledby=\"downshift-1-label\"]"],"failureSummary":"Fix all of the following:\n  Invalid ARIA attribute value: aria-labelledby=\"downshift-1-label\""}]}]},{"id":"20191126","route":{"id":"get-started_details","path":"/get-started/details"},"needsManualCheck":false,"violations":[{"id":"aria-input-field-name","impact":"serious","tags":["wcag2a","wcag412"],"description":"Ensures every ARIA input field has an accessible name","help":"ARIA input fields have an accessible name","helpUrl":"https://dequeuniversity.com/rules/axe/3.3/aria-input-field-name?application=axe-puppeteer","nodes":[{"any":[{"id":"aria-label","data":null,"relatedNodes":[],"impact":"serious","message":"aria-label attribute does not exist or is empty"},{"id":"aria-labelledby","data":null,"relatedNodes":[],"impact":"serious","message":"aria-labelledby attribute does not exist, references elements that do not exist or references elements that are empty"},{"id":"non-empty-title","data":null,"relatedNodes":[],"impact":"serious","message":"Element has no title attribute or the title attribute is empty"}],"all":[],"none":[],"impact":"serious","html":"<div tabindex=\"0\" class=\"SomethingElse_main__16if9\" data-testid=\"something-else\" role=\"combobox\" aria-expanded=\"false\" aria-haspopup=\"listbox\" aria-labelledby=\"downshift-0-label\">","target":["div[aria-labelledby=\"downshift-0-label\"]"],"failureSummary":"Fix any of the following:\n  aria-label attribute does not exist or is empty\n  aria-labelledby attribute does not exist, references elements that do not exist or references elements that are empty\n  Element has no title attribute or the title attribute is empty"},{"any":[{"id":"aria-label","data":null,"relatedNodes":[],"impact":"serious","message":"aria-label attribute does not exist or is empty"},{"id":"aria-labelledby","data":null,"relatedNodes":[],"impact":"serious","message":"aria-labelledby attribute does not exist, references elements that do not exist or references elements that are empty"},{"id":"non-empty-title","data":null,"relatedNodes":[],"impact":"serious","message":"Element has no title attribute or the title attribute is empty"}],"all":[],"none":[],"impact":"serious","html":"<div tabindex=\"0\" class=\"SomethingElse_main__16if9\" data-testid=\"something-else\" role=\"combobox\" aria-expanded=\"false\" aria-haspopup=\"listbox\" aria-labelledby=\"downshift-1-label\">","target":["div[aria-labelledby=\"downshift-1-label\"]"],"failureSummary":"Fix any of the following:\n  aria-label attribute does not exist or is empty\n  aria-labelledby attribute does not exist, references elements that do not exist or references elements that are empty\n  Element has no title attribute or the title attribute is empty"}]},{"id":"aria-required-children","impact":"critical","tags":["cat.aria","wcag2a","wcag131"],"description":"Ensures elements with an ARIA role that require child roles contain them","help":"Certain ARIA roles must contain particular children","helpUrl":"https://dequeuniversity.com/rules/axe/3.3/aria-required-children?application=axe-puppeteer","nodes":[{"any":[{"id":"aria-required-children","data":["textbox"],"relatedNodes":[],"impact":"critical","message":"Required ARIA child role not present: textbox"}],"all":[],"none":[],"impact":"critical","html":"<div tabindex=\"0\" class=\"SomethingElse_main__16if9\" data-testid=\"something-else\" role=\"combobox\" aria-expanded=\"false\" aria-haspopup=\"listbox\" aria-labelledby=\"downshift-0-label\">","target":["div[aria-labelledby=\"downshift-0-label\"]"],"failureSummary":"Fix any of the following:\n  Required ARIA child role not present: textbox"},{"any":[{"id":"aria-required-children","data":["textbox"],"relatedNodes":[],"impact":"critical","message":"Required ARIA child role not present: textbox"}],"all":[],"none":[],"impact":"critical","html":"<div tabindex=\"0\" class=\"SomethingElse_main__16if9\" data-testid=\"something-else\" role=\"combobox\" aria-expanded=\"false\" aria-haspopup=\"listbox\" aria-labelledby=\"downshift-1-label\">","target":["div[aria-labelledby=\"downshift-1-label\"]"],"failureSummary":"Fix any of the following:\n  Required ARIA child role not present: textbox"}]},{"id":"aria-valid-attr-value","impact":"critical","tags":["cat.aria","wcag2a","wcag412"],"description":"Ensures all ARIA attributes have valid values","help":"ARIA attributes must conform to valid values","helpUrl":"https://dequeuniversity.com/rules/axe/3.3/aria-valid-attr-value?application=axe-puppeteer","nodes":[{"any":[],"all":[{"id":"aria-valid-attr-value","data":["aria-labelledby=\"downshift-0-label\""],"relatedNodes":[],"impact":"critical","message":"Invalid ARIA attribute value: aria-labelledby=\"downshift-0-label\""}],"none":[],"impact":"critical","html":"<div tabindex=\"0\" class=\"SomethingElse_main__16if9\" data-testid=\"something-else\" role=\"combobox\" aria-expanded=\"false\" aria-haspopup=\"listbox\" aria-labelledby=\"downshift-0-label\">","target":["div[aria-labelledby=\"downshift-0-label\"]"],"failureSummary":"Fix all of the following:\n  Invalid ARIA attribute value: aria-labelledby=\"downshift-0-label\""},{"any":[],"all":[{"id":"aria-valid-attr-value","data":["aria-labelledby=\"downshift-1-label\""],"relatedNodes":[],"impact":"critical","message":"Invalid ARIA attribute value: aria-labelledby=\"downshift-1-label\""}],"none":[],"impact":"critical","html":"<div tabindex=\"0\" class=\"SomethingElse_main__16if9\" data-testid=\"something-else\" role=\"combobox\" aria-expanded=\"false\" aria-haspopup=\"listbox\" aria-labelledby=\"downshift-1-label\">","target":["div[aria-labelledby=\"downshift-1-label\"]"],"failureSummary":"Fix all of the following:\n  Invalid ARIA attribute value: aria-labelledby=\"downshift-1-label\""}]}]},{"id":"20191203","route":{"id":"get-started_details","path":"/get-started/details"},"needsManualCheck":false,"violations":[{"id":"aria-input-field-name","impact":"serious","tags":["wcag2a","wcag412"],"description":"Ensures every ARIA input field has an accessible name","help":"ARIA input fields have an accessible name","helpUrl":"https://dequeuniversity.com/rules/axe/3.3/aria-input-field-name?application=axe-puppeteer","nodes":[{"any":[{"id":"aria-label","data":null,"relatedNodes":[],"impact":"serious","message":"aria-label attribute does not exist or is empty"},{"id":"aria-labelledby","data":null,"relatedNodes":[],"impact":"serious","message":"aria-labelledby attribute does not exist, references elements that do not exist or references elements that are empty"},{"id":"non-empty-title","data":null,"relatedNodes":[],"impact":"serious","message":"Element has no title attribute or the title attribute is empty"}],"all":[],"none":[],"impact":"serious","html":"<div tabindex=\"0\" class=\"SomethingElse_main__16if9\" data-testid=\"something-else\" role=\"combobox\" aria-expanded=\"false\" aria-haspopup=\"listbox\" aria-labelledby=\"downshift-0-label\">","target":["div[aria-labelledby=\"downshift-0-label\"]"],"failureSummary":"Fix any of the following:\n  aria-label attribute does not exist or is empty\n  aria-labelledby attribute does not exist, references elements that do not exist or references elements that are empty\n  Element has no title attribute or the title attribute is empty"},{"any":[{"id":"aria-label","data":null,"relatedNodes":[],"impact":"serious","message":"aria-label attribute does not exist or is empty"},{"id":"aria-labelledby","data":null,"relatedNodes":[],"impact":"serious","message":"aria-labelledby attribute does not exist, references elements that do not exist or references elements that are empty"},{"id":"non-empty-title","data":null,"relatedNodes":[],"impact":"serious","message":"Element has no title attribute or the title attribute is empty"}],"all":[],"none":[],"impact":"serious","html":"<div tabindex=\"0\" class=\"SomethingElse_main__16if9\" data-testid=\"something-else\" role=\"combobox\" aria-expanded=\"false\" aria-haspopup=\"listbox\" aria-labelledby=\"downshift-1-label\">","target":["div[aria-labelledby=\"downshift-1-label\"]"],"failureSummary":"Fix any of the following:\n  aria-label attribute does not exist or is empty\n  aria-labelledby attribute does not exist, references elements that do not exist or references elements that are empty\n  Element has no title attribute or the title attribute is empty"}]},{"id":"aria-required-children","impact":"critical","tags":["cat.aria","wcag2a","wcag131"],"description":"Ensures elements with an ARIA role that require child roles contain them","help":"Certain ARIA roles must contain particular children","helpUrl":"https://dequeuniversity.com/rules/axe/3.3/aria-required-children?application=axe-puppeteer","nodes":[{"any":[{"id":"aria-required-children","data":["textbox"],"relatedNodes":[],"impact":"critical","message":"Required ARIA child role not present: textbox"}],"all":[],"none":[],"impact":"critical","html":"<div tabindex=\"0\" class=\"SomethingElse_main__16if9\" data-testid=\"something-else\" role=\"combobox\" aria-expanded=\"false\" aria-haspopup=\"listbox\" aria-labelledby=\"downshift-0-label\">","target":["div[aria-labelledby=\"downshift-0-label\"]"],"failureSummary":"Fix any of the following:\n  Required ARIA child role not present: textbox"},{"any":[{"id":"aria-required-children","data":["textbox"],"relatedNodes":[],"impact":"critical","message":"Required ARIA child role not present: textbox"}],"all":[],"none":[],"impact":"critical","html":"<div tabindex=\"0\" class=\"SomethingElse_main__16if9\" data-testid=\"something-else\" role=\"combobox\" aria-expanded=\"false\" aria-haspopup=\"listbox\" aria-labelledby=\"downshift-1-label\">","target":["div[aria-labelledby=\"downshift-1-label\"]"],"failureSummary":"Fix any of the following:\n  Required ARIA child role not present: textbox"}]},{"id":"aria-valid-attr-value","impact":"critical","tags":["cat.aria","wcag2a","wcag412"],"description":"Ensures all ARIA attributes have valid values","help":"ARIA attributes must conform to valid values","helpUrl":"https://dequeuniversity.com/rules/axe/3.3/aria-valid-attr-value?application=axe-puppeteer","nodes":[{"any":[],"all":[{"id":"aria-valid-attr-value","data":["aria-labelledby=\"downshift-0-label\""],"relatedNodes":[],"impact":"critical","message":"Invalid ARIA attribute value: aria-labelledby=\"downshift-0-label\""}],"none":[],"impact":"critical","html":"<div tabindex=\"0\" class=\"SomethingElse_main__16if9\" data-testid=\"something-else\" role=\"combobox\" aria-expanded=\"false\" aria-haspopup=\"listbox\" aria-labelledby=\"downshift-0-label\">","target":["div[aria-labelledby=\"downshift-0-label\"]"],"failureSummary":"Fix all of the following:\n  Invalid ARIA attribute value: aria-labelledby=\"downshift-0-label\""},{"any":[],"all":[{"id":"aria-valid-attr-value","data":["aria-labelledby=\"downshift-1-label\""],"relatedNodes":[],"impact":"critical","message":"Invalid ARIA attribute value: aria-labelledby=\"downshift-1-label\""}],"none":[],"impact":"critical","html":"<div tabindex=\"0\" class=\"SomethingElse_main__16if9\" data-testid=\"something-else\" role=\"combobox\" aria-expanded=\"false\" aria-haspopup=\"listbox\" aria-labelledby=\"downshift-1-label\">","target":["div[aria-labelledby=\"downshift-1-label\"]"],"failureSummary":"Fix all of the following:\n  Invalid ARIA attribute value: aria-labelledby=\"downshift-1-label\""}]},{"id":"color-contrast","impact":"serious","tags":["cat.color","wcag2aa","wcag143"],"description":"Ensures the contrast between foreground and background colors meets WCAG 2 AA contrast ratio thresholds","help":"Elements must have sufficient color contrast","helpUrl":"https://dequeuniversity.com/rules/axe/3.3/color-contrast?application=axe-puppeteer","nodes":[{"any":[{"id":"color-contrast","data":{"fgColor":"#ff00ff","bgColor":"#ffffff","contrastRatio":3.13,"fontSize":"9.8pt (13px)","fontWeight":"normal","expectedContrastRatio":"4.5:1"},"relatedNodes":[{"html":"<div class=\"ContentPanel_panel__3HtKp ContentPanel_main__1HrCm\">","target":[".ContentPanel_panel__3HtKp"]}],"impact":"serious","message":"Element has insufficient color contrast of 3.13 (foreground color: #ff00ff, background color: #ffffff, font size: 9.8pt (13px), font weight: normal). Expected contrast ratio of 4.5:1"}],"all":[],"none":[],"impact":"serious","html":"<button class=\"Pill_Pill__Dd4Z9\" aria-pressed=\"false\" type=\"button\">Activewear</button>","target":["section[data-testid=\"needs\"] > .PillGroup_main__27VFN > .Pill_Pill__Dd4Z9[type=\"button\"]:nth-child(1)"],"failureSummary":"Fix any of the following:\n  Element has insufficient color contrast of 3.13 (foreground color: #ff00ff, background color: #ffffff, font size: 9.8pt (13px), font weight: normal). Expected contrast ratio of 4.5:1"},{"any":[{"id":"color-contrast","data":{"fgColor":"#ff00ff","bgColor":"#ffffff","contrastRatio":3.13,"fontSize":"9.8pt (13px)","fontWeight":"normal","expectedContrastRatio":"4.5:1"},"relatedNodes":[{"html":"<div class=\"ContentPanel_panel__3HtKp ContentPanel_main__1HrCm\">","target":[".ContentPanel_panel__3HtKp"]}],"impact":"serious","message":"Element has insufficient color contrast of 3.13 (foreground color: #ff00ff, background color: #ffffff, font size: 9.8pt (13px), font weight: normal). Expected contrast ratio of 4.5:1"}],"all":[],"none":[],"impact":"serious","html":"<button class=\"Pill_Pill__Dd4Z9\" aria-pressed=\"false\" type=\"button\">Long Sleeve Tee</button>","target":["section[data-testid=\"needs\"] > .PillGroup_main__27VFN > .Pill_Pill__Dd4Z9[type=\"button\"]:nth-child(2)"],"failureSummary":"Fix any of the following:\n  Element has insufficient color contrast of 3.13 (foreground color: #ff00ff, background color: #ffffff, font size: 9.8pt (13px), font weight: normal). Expected contrast ratio of 4.5:1"},{"any":[{"id":"color-contrast","data":{"fgColor":"#ff00ff","bgColor":"#ffffff","contrastRatio":3.13,"fontSize":"9.8pt (13px)","fontWeight":"normal","expectedContrastRatio":"4.5:1"},"relatedNodes":[{"html":"<div class=\"ContentPanel_panel__3HtKp ContentPanel_main__1HrCm\">","target":[".ContentPanel_panel__3HtKp"]}],"impact":"serious","message":"Element has insufficient color contrast of 3.13 (foreground color: #ff00ff, background color: #ffffff, font size: 9.8pt (13px), font weight: normal). Expected contrast ratio of 4.5:1"}],"all":[],"none":[],"impact":"serious","html":"<button class=\"Pill_Pill__Dd4Z9\" aria-pressed=\"false\" type=\"button\">Button Down Shirts</button>","target":["section[data-testid=\"needs\"] > .PillGroup_main__27VFN > .Pill_Pill__Dd4Z9[type=\"button\"]:nth-child(3)"],"failureSummary":"Fix any of the following:\n  Element has insufficient color contrast of 3.13 (foreground color: #ff00ff, background color: #ffffff, font size: 9.8pt (13px), font weight: normal). Expected contrast ratio of 4.5:1"},{"any":[{"id":"color-contrast","data":{"fgColor":"#ff00ff","bgColor":"#ffffff","contrastRatio":3.13,"fontSize":"9.8pt (13px)","fontWeight":"normal","expectedContrastRatio":"4.5:1"},"relatedNodes":[{"html":"<div class=\"ContentPanel_panel__3HtKp ContentPanel_main__1HrCm\">","target":[".ContentPanel_panel__3HtKp"]}],"impact":"serious","message":"Element has insufficient color contrast of 3.13 (foreground color: #ff00ff, background color: #ffffff, font size: 9.8pt (13px), font weight: normal). Expected contrast ratio of 4.5:1"}],"all":[],"none":[],"impact":"serious","html":"<button class=\"Pill_Pill__Dd4Z9\" aria-pressed=\"false\" type=\"button\">Scarf</button>","target":["section[data-testid=\"needs\"] > .PillGroup_main__27VFN > .Pill_Pill__Dd4Z9[type=\"button\"]:nth-child(4)"],"failureSummary":"Fix any of the following:\n  Element has insufficient color contrast of 3.13 (foreground color: #ff00ff, background color: #ffffff, font size: 9.8pt (13px), font weight: normal). Expected contrast ratio of 4.5:1"},{"any":[{"id":"color-contrast","data":{"fgColor":"#ff00ff","bgColor":"#ffffff","contrastRatio":3.13,"fontSize":"9.8pt (13px)","fontWeight":"normal","expectedContrastRatio":"4.5:1"},"relatedNodes":[{"html":"<div class=\"ContentPanel_panel__3HtKp ContentPanel_main__1HrCm\">","target":[".ContentPanel_panel__3HtKp"]}],"impact":"serious","message":"Element has insufficient color contrast of 3.13 (foreground color: #ff00ff, background color: #ffffff, font size: 9.8pt (13px), font weight: normal). Expected contrast ratio of 4.5:1"}],"all":[],"none":[],"impact":"serious","html":"<button class=\"Pill_Pill__Dd4Z9\" aria-pressed=\"false\" type=\"button\">Hats</button>","target":["section[data-testid=\"needs\"] > .PillGroup_main__27VFN > .Pill_Pill__Dd4Z9[type=\"button\"]:nth-child(5)"],"failureSummary":"Fix any of the following:\n  Element has insufficient color contrast of 3.13 (foreground color: #ff00ff, background color: #ffffff, font size: 9.8pt (13px), font weight: normal). Expected contrast ratio of 4.5:1"},{"any":[{"id":"color-contrast","data":{"fgColor":"#ff00ff","bgColor":"#ffffff","contrastRatio":3.13,"fontSize":"9.8pt (13px)","fontWeight":"normal","expectedContrastRatio":"4.5:1"},"relatedNodes":[{"html":"<div class=\"ContentPanel_panel__3HtKp ContentPanel_main__1HrCm\">","target":[".ContentPanel_panel__3HtKp"]}],"impact":"serious","message":"Element has insufficient color contrast of 3.13 (foreground color: #ff00ff, background color: #ffffff, font size: 9.8pt (13px), font weight: normal). Expected contrast ratio of 4.5:1"}],"all":[],"none":[],"impact":"serious","html":"<button class=\"Pill_Pill__Dd4Z9\" aria-pressed=\"false\" type=\"button\">Winter Coat</button>","target":[".Pill_Pill__Dd4Z9[type=\"button\"]:nth-child(6)"],"failureSummary":"Fix any of the following:\n  Element has insufficient color contrast of 3.13 (foreground color: #ff00ff, background color: #ffffff, font size: 9.8pt (13px), font weight: normal). Expected contrast ratio of 4.5:1"},{"any":[{"id":"color-contrast","data":{"fgColor":"#ff00ff","bgColor":"#ffffff","contrastRatio":3.13,"fontSize":"9.8pt (13px)","fontWeight":"normal","expectedContrastRatio":"4.5:1"},"relatedNodes":[{"html":"<div class=\"ContentPanel_panel__3HtKp ContentPanel_main__1HrCm\">","target":[".ContentPanel_panel__3HtKp"]}],"impact":"serious","message":"Element has insufficient color contrast of 3.13 (foreground color: #ff00ff, background color: #ffffff, font size: 9.8pt (13px), font weight: normal). Expected contrast ratio of 4.5:1"}],"all":[],"none":[],"impact":"serious","html":"<button class=\"Pill_Pill__Dd4Z9\" aria-pressed=\"false\" type=\"button\">Crossbody Bags</button>","target":[".Pill_Pill__Dd4Z9[type=\"button\"]:nth-child(7)"],"failureSummary":"Fix any of the following:\n  Element has insufficient color contrast of 3.13 (foreground color: #ff00ff, background color: #ffffff, font size: 9.8pt (13px), font weight: normal). Expected contrast ratio of 4.5:1"},{"any":[{"id":"color-contrast","data":{"fgColor":"#ff00ff","bgColor":"#ffffff","contrastRatio":3.13,"fontSize":"9.8pt (13px)","fontWeight":"normal","expectedContrastRatio":"4.5:1"},"relatedNodes":[{"html":"<div class=\"ContentPanel_panel__3HtKp ContentPanel_main__1HrCm\">","target":[".ContentPanel_panel__3HtKp"]}],"impact":"serious","message":"Element has insufficient color contrast of 3.13 (foreground color: #ff00ff, background color: #ffffff, font size: 9.8pt (13px), font weight: normal). Expected contrast ratio of 4.5:1"}],"all":[],"none":[],"impact":"serious","html":"<button class=\"Pill_Pill__Dd4Z9\" aria-pressed=\"false\" type=\"button\">Pumps</button>","target":[".Pill_Pill__Dd4Z9[type=\"button\"]:nth-child(8)"],"failureSummary":"Fix any of the following:\n  Element has insufficient color contrast of 3.13 (foreground color: #ff00ff, background color: #ffffff, font size: 9.8pt (13px), font weight: normal). Expected contrast ratio of 4.5:1"},{"any":[{"id":"color-contrast","data":{"fgColor":"#ff00ff","bgColor":"#ffffff","contrastRatio":3.13,"fontSize":"9.8pt (13px)","fontWeight":"normal","expectedContrastRatio":"4.5:1"},"relatedNodes":[{"html":"<div class=\"ContentPanel_panel__3HtKp ContentPanel_main__1HrCm\">","target":[".ContentPanel_panel__3HtKp"]}],"impact":"serious","message":"Element has insufficient color contrast of 3.13 (foreground color: #ff00ff, background color: #ffffff, font size: 9.8pt (13px), font weight: normal). Expected contrast ratio of 4.5:1"}],"all":[],"none":[],"impact":"serious","html":"<button class=\"Pill_Pill__Dd4Z9\" aria-pressed=\"false\" type=\"button\">Booties</button>","target":[".Pill_Pill__Dd4Z9[type=\"button\"]:nth-child(9)"],"failureSummary":"Fix any of the following:\n  Element has insufficient color contrast of 3.13 (foreground color: #ff00ff, background color: #ffffff, font size: 9.8pt (13px), font weight: normal). Expected contrast ratio of 4.5:1"},{"any":[{"id":"color-contrast","data":{"fgColor":"#ff00ff","bgColor":"#ffffff","contrastRatio":3.13,"fontSize":"9.8pt (13px)","fontWeight":"normal","expectedContrastRatio":"4.5:1"},"relatedNodes":[{"html":"<div class=\"ContentPanel_panel__3HtKp ContentPanel_main__1HrCm\">","target":[".ContentPanel_panel__3HtKp"]}],"impact":"serious","message":"Element has insufficient color contrast of 3.13 (foreground color: #ff00ff, background color: #ffffff, font size: 9.8pt (13px), font weight: normal). Expected contrast ratio of 4.5:1"}],"all":[],"none":[],"impact":"serious","html":"<button class=\"Pill_Pill__Dd4Z9\" aria-pressed=\"false\" type=\"button\">Pants</button>","target":[".Pill_Pill__Dd4Z9[type=\"button\"]:nth-child(10)"],"failureSummary":"Fix any of the following:\n  Element has insufficient color contrast of 3.13 (foreground color: #ff00ff, background color: #ffffff, font size: 9.8pt (13px), font weight: normal). Expected contrast ratio of 4.5:1"},{"any":[{"id":"color-contrast","data":{"fgColor":"#ff00ff","bgColor":"#ffffff","contrastRatio":3.13,"fontSize":"9.8pt (13px)","fontWeight":"normal","expectedContrastRatio":"4.5:1"},"relatedNodes":[{"html":"<div class=\"ContentPanel_panel__3HtKp ContentPanel_main__1HrCm\">","target":[".ContentPanel_panel__3HtKp"]}],"impact":"serious","message":"Element has insufficient color contrast of 3.13 (foreground color: #ff00ff, background color: #ffffff, font size: 9.8pt (13px), font weight: normal). Expected contrast ratio of 4.5:1"}],"all":[],"none":[],"impact":"serious","html":"<button class=\"Pill_Pill__Dd4Z9\" aria-pressed=\"false\" type=\"button\">Dresses</button>","target":[".Pill_Pill__Dd4Z9[type=\"button\"]:nth-child(11)"],"failureSummary":"Fix any of the following:\n  Element has insufficient color contrast of 3.13 (foreground color: #ff00ff, background color: #ffffff, font size: 9.8pt (13px), font weight: normal). Expected contrast ratio of 4.5:1"},{"any":[{"id":"color-contrast","data":{"fgColor":"#ff00ff","bgColor":"#ffffff","contrastRatio":3.13,"fontSize":"9.8pt (13px)","fontWeight":"normal","expectedContrastRatio":"4.5:1"},"relatedNodes":[{"html":"<div class=\"ContentPanel_panel__3HtKp ContentPanel_main__1HrCm\">","target":[".ContentPanel_panel__3HtKp"]}],"impact":"serious","message":"Element has insufficient color contrast of 3.13 (foreground color: #ff00ff, background color: #ffffff, font size: 9.8pt (13px), font weight: normal). Expected contrast ratio of 4.5:1"}],"all":[],"none":[],"impact":"serious","html":"<button class=\"Pill_Pill__Dd4Z9\" aria-pressed=\"false\" type=\"button\">Jeans</button>","target":[".Pill_Pill__Dd4Z9[type=\"button\"]:nth-child(12)"],"failureSummary":"Fix any of the following:\n  Element has insufficient color contrast of 3.13 (foreground color: #ff00ff, background color: #ffffff, font size: 9.8pt (13px), font weight: normal). Expected contrast ratio of 4.5:1"},{"any":[{"id":"color-contrast","data":{"fgColor":"#ff00ff","bgColor":"#ffffff","contrastRatio":3.13,"fontSize":"9.8pt (13px)","fontWeight":"normal","expectedContrastRatio":"4.5:1"},"relatedNodes":[{"html":"<div class=\"ContentPanel_panel__3HtKp ContentPanel_main__1HrCm\">","target":[".ContentPanel_panel__3HtKp"]}],"impact":"serious","message":"Element has insufficient color contrast of 3.13 (foreground color: #ff00ff, background color: #ffffff, font size: 9.8pt (13px), font weight: normal). Expected contrast ratio of 4.5:1"}],"all":[],"none":[],"impact":"serious","html":"<button class=\"Pill_Pill__Dd4Z9\" aria-pressed=\"false\" type=\"button\">Sweaters</button>","target":[".Pill_Pill__Dd4Z9[type=\"button\"]:nth-child(13)"],"failureSummary":"Fix any of the following:\n  Element has insufficient color contrast of 3.13 (foreground color: #ff00ff, background color: #ffffff, font size: 9.8pt (13px), font weight: normal). Expected contrast ratio of 4.5:1"},{"any":[{"id":"color-contrast","data":{"fgColor":"#ff00ff","bgColor":"#ffffff","contrastRatio":3.13,"fontSize":"9.8pt (13px)","fontWeight":"normal","expectedContrastRatio":"4.5:1"},"relatedNodes":[{"html":"<div class=\"ContentPanel_panel__3HtKp ContentPanel_main__1HrCm\">","target":[".ContentPanel_panel__3HtKp"]}],"impact":"serious","message":"Element has insufficient color contrast of 3.13 (foreground color: #ff00ff, background color: #ffffff, font size: 9.8pt (13px), font weight: normal). Expected contrast ratio of 4.5:1"}],"all":[],"none":[],"impact":"serious","html":"<button class=\"Pill_Pill__Dd4Z9\" aria-pressed=\"false\" type=\"button\">Leather Jacket</button>","target":[".Pill_Pill__Dd4Z9[type=\"button\"]:nth-child(14)"],"failureSummary":"Fix any of the following:\n  Element has insufficient color contrast of 3.13 (foreground color: #ff00ff, background color: #ffffff, font size: 9.8pt (13px), font weight: normal). Expected contrast ratio of 4.5:1"},{"any":[{"id":"color-contrast","data":{"fgColor":"#ff00ff","bgColor":"#ffffff","contrastRatio":3.13,"fontSize":"9.8pt (13px)","fontWeight":"normal","expectedContrastRatio":"4.5:1"},"relatedNodes":[{"html":"<div class=\"ContentPanel_panel__3HtKp ContentPanel_main__1HrCm\">","target":[".ContentPanel_panel__3HtKp"]}],"impact":"serious","message":"Element has insufficient color contrast of 3.13 (foreground color: #ff00ff, background color: #ffffff, font size: 9.8pt (13px), font weight: normal). Expected contrast ratio of 4.5:1"}],"all":[],"none":[],"impact":"serious","html":"<button class=\"Pill_Pill__Dd4Z9\" aria-pressed=\"false\" type=\"button\">Blazer</button>","target":[".Pill_Pill__Dd4Z9[type=\"button\"]:nth-child(15)"],"failureSummary":"Fix any of the following:\n  Element has insufficient color contrast of 3.13 (foreground color: #ff00ff, background color: #ffffff, font size: 9.8pt (13px), font weight: normal). Expected contrast ratio of 4.5:1"},{"any":[{"id":"color-contrast","data":{"fgColor":"#ff00ff","bgColor":"#ffffff","contrastRatio":3.13,"fontSize":"9.8pt (13px)","fontWeight":"normal","expectedContrastRatio":"4.5:1"},"relatedNodes":[{"html":"<div class=\"ContentPanel_panel__3HtKp ContentPanel_main__1HrCm\">","target":[".ContentPanel_panel__3HtKp"]}],"impact":"serious","message":"Element has insufficient color contrast of 3.13 (foreground color: #ff00ff, background color: #ffffff, font size: 9.8pt (13px), font weight: normal). Expected contrast ratio of 4.5:1"}],"all":[],"none":[],"impact":"serious","html":"<button class=\"Pill_Pill__Dd4Z9\" aria-pressed=\"false\" type=\"button\">Blouses</button>","target":[".Pill_Pill__Dd4Z9[type=\"button\"]:nth-child(16)"],"failureSummary":"Fix any of the following:\n  Element has insufficient color contrast of 3.13 (foreground color: #ff00ff, background color: #ffffff, font size: 9.8pt (13px), font weight: normal). Expected contrast ratio of 4.5:1"},{"any":[{"id":"color-contrast","data":{"fgColor":"#ff00ff","bgColor":"#ffffff","contrastRatio":3.13,"fontSize":"12.0pt (16px)","fontWeight":"normal","expectedContrastRatio":"4.5:1"},"relatedNodes":[{"html":"<textarea id=\"stylist_avoid\" placeholder=\"E.g. shoes, jewelry, sweatshirts, etc.\" data-testid=\"stylist-avoid\" class=\"Note_Note__2LN1F\"></textarea>","target":["#stylist_avoid"]}],"impact":"serious","message":"Element has insufficient color contrast of 3.13 (foreground color: #ff00ff, background color: #ffffff, font size: 12.0pt (16px), font weight: normal). Expected contrast ratio of 4.5:1"}],"all":[],"none":[],"impact":"serious","html":"<textarea id=\"stylist_avoid\" placeholder=\"E.g. shoes, jewelry, sweatshirts, etc.\" data-testid=\"stylist-avoid\" class=\"Note_Note__2LN1F\"></textarea>","target":["#stylist_avoid"],"failureSummary":"Fix any of the following:\n  Element has insufficient color contrast of 3.13 (foreground color: #ff00ff, background color: #ffffff, font size: 12.0pt (16px), font weight: normal). Expected contrast ratio of 4.5:1"},{"any":[{"id":"color-contrast","data":{"fgColor":"#ff00ff","bgColor":"#ffffff","contrastRatio":3.13,"fontSize":"9.8pt (13px)","fontWeight":"normal","expectedContrastRatio":"4.5:1"},"relatedNodes":[{"html":"<div class=\"ContentPanel_panel__3HtKp ContentPanel_main__1HrCm\">","target":[".ContentPanel_panel__3HtKp"]}],"impact":"serious","message":"Element has insufficient color contrast of 3.13 (foreground color: #ff00ff, background color: #ffffff, font size: 9.8pt (13px), font weight: normal). Expected contrast ratio of 4.5:1"}],"all":[],"none":[],"impact":"serious","html":"<button class=\"Pill_Pill__Dd4Z9\" aria-pressed=\"false\" type=\"button\">Work</button>","target":["section[data-testid=\"purposes\"] > .PillGroup_main__27VFN > .Pill_Pill__Dd4Z9[type=\"button\"]:nth-child(1)"],"failureSummary":"Fix any of the following:\n  Element has insufficient color contrast of 3.13 (foreground color: #ff00ff, background color: #ffffff, font size: 9.8pt (13px), font weight: normal). Expected contrast ratio of 4.5:1"},{"any":[{"id":"color-contrast","data":{"fgColor":"#ff00ff","bgColor":"#ffffff","contrastRatio":3.13,"fontSize":"9.8pt (13px)","fontWeight":"normal","expectedContrastRatio":"4.5:1"},"relatedNodes":[{"html":"<div class=\"ContentPanel_panel__3HtKp ContentPanel_main__1HrCm\">","target":[".ContentPanel_panel__3HtKp"]}],"impact":"serious","message":"Element has insufficient color contrast of 3.13 (foreground color: #ff00ff, background color: #ffffff, font size: 9.8pt (13px), font weight: normal). Expected contrast ratio of 4.5:1"}],"all":[],"none":[],"impact":"serious","html":"<button class=\"Pill_Pill__Dd4Z9\" aria-pressed=\"false\" type=\"button\">Weekend</button>","target":["section[data-testid=\"purposes\"] > .PillGroup_main__27VFN > .Pill_Pill__Dd4Z9[type=\"button\"]:nth-child(2)"],"failureSummary":"Fix any of the following:\n  Element has insufficient color contrast of 3.13 (foreground color: #ff00ff, background color: #ffffff, font size: 9.8pt (13px), font weight: normal). Expected contrast ratio of 4.5:1"},{"any":[{"id":"color-contrast","data":{"fgColor":"#ff00ff","bgColor":"#ffffff","contrastRatio":3.13,"fontSize":"9.8pt (13px)","fontWeight":"normal","expectedContrastRatio":"4.5:1"},"relatedNodes":[{"html":"<div class=\"ContentPanel_panel__3HtKp ContentPanel_main__1HrCm\">","target":[".ContentPanel_panel__3HtKp"]}],"impact":"serious","message":"Element has insufficient color contrast of 3.13 (foreground color: #ff00ff, background color: #ffffff, font size: 9.8pt (13px), font weight: normal). Expected contrast ratio of 4.5:1"}],"all":[],"none":[],"impact":"serious","html":"<button class=\"Pill_Pill__Dd4Z9\" aria-pressed=\"false\" type=\"button\">Wardrobe Refresh</button>","target":["section[data-testid=\"purposes\"] > .PillGroup_main__27VFN > .Pill_Pill__Dd4Z9[type=\"button\"]:nth-child(3)"],"failureSummary":"Fix any of the following:\n  Element has insufficient color contrast of 3.13 (foreground color: #ff00ff, background color: #ffffff, font size: 9.8pt (13px), font weight: normal). Expected contrast ratio of 4.5:1"},{"any":[{"id":"color-contrast","data":{"fgColor":"#ff00ff","bgColor":"#ffffff","contrastRatio":3.13,"fontSize":"9.8pt (13px)","fontWeight":"normal","expectedContrastRatio":"4.5:1"},"relatedNodes":[{"html":"<div class=\"ContentPanel_panel__3HtKp ContentPanel_main__1HrCm\">","target":[".ContentPanel_panel__3HtKp"]}],"impact":"serious","message":"Element has insufficient color contrast of 3.13 (foreground color: #ff00ff, background color: #ffffff, font size: 9.8pt (13px), font weight: normal). Expected contrast ratio of 4.5:1"}],"all":[],"none":[],"impact":"serious","html":"<button class=\"Pill_Pill__Dd4Z9\" aria-pressed=\"false\" type=\"button\">Wedding</button>","target":["section[data-testid=\"purposes\"] > .PillGroup_main__27VFN > .Pill_Pill__Dd4Z9[type=\"button\"]:nth-child(4)"],"failureSummary":"Fix any of the following:\n  Element has insufficient color contrast of 3.13 (foreground color: #ff00ff, background color: #ffffff, font size: 9.8pt (13px), font weight: normal). Expected contrast ratio of 4.5:1"},{"any":[{"id":"color-contrast","data":{"fgColor":"#ff00ff","bgColor":"#ffffff","contrastRatio":3.13,"fontSize":"9.8pt (13px)","fontWeight":"normal","expectedContrastRatio":"4.5:1"},"relatedNodes":[{"html":"<div class=\"ContentPanel_panel__3HtKp ContentPanel_main__1HrCm\">","target":[".ContentPanel_panel__3HtKp"]}],"impact":"serious","message":"Element has insufficient color contrast of 3.13 (foreground color: #ff00ff, background color: #ffffff, font size: 9.8pt (13px), font weight: normal). Expected contrast ratio of 4.5:1"}],"all":[],"none":[],"impact":"serious","html":"<button class=\"Pill_Pill__Dd4Z9\" aria-pressed=\"false\" type=\"button\">Vacation</button>","target":["section[data-testid=\"purposes\"] > .PillGroup_main__27VFN > .Pill_Pill__Dd4Z9[type=\"button\"]:nth-child(5)"],"failureSummary":"Fix any of the following:\n  Element has insufficient color contrast of 3.13 (foreground color: #ff00ff, background color: #ffffff, font size: 9.8pt (13px), font weight: normal). Expected contrast ratio of 4.5:1"},{"any":[{"id":"color-contrast","data":{"fgColor":"#ff00ff","bgColor":"#ffffff","contrastRatio":3.13,"fontSize":"12.0pt (16px)","fontWeight":"normal","expectedContrastRatio":"4.5:1"},"relatedNodes":[{"html":"<textarea id=\"stylist_note\" placeholder=\"E.g. upcoming events, style preferences, color, etc.\" data-testid=\"stylist-note\" class=\"Note_Note__2LN1F\"></textarea>","target":["#stylist_note"]}],"impact":"serious","message":"Element has insufficient color contrast of 3.13 (foreground color: #ff00ff, background color: #ffffff, font size: 12.0pt (16px), font weight: normal). Expected contrast ratio of 4.5:1"}],"all":[],"none":[],"impact":"serious","html":"<textarea id=\"stylist_note\" placeholder=\"E.g. upcoming events, style preferences, color, etc.\" data-testid=\"stylist-note\" class=\"Note_Note__2LN1F\"></textarea>","target":["#stylist_note"],"failureSummary":"Fix any of the following:\n  Element has insufficient color contrast of 3.13 (foreground color: #ff00ff, background color: #ffffff, font size: 12.0pt (16px), font weight: normal). Expected contrast ratio of 4.5:1"},{"any":[{"id":"color-contrast","data":{"fgColor":"#ff00ff","bgColor":"#ffffff","contrastRatio":3.13,"fontSize":"12.0pt (16px)","fontWeight":"normal","expectedContrastRatio":"4.5:1"},"relatedNodes":[{"html":"<div class=\"ContentPanel_panel__3HtKp ContentPanel_main__1HrCm\">","target":[".ContentPanel_panel__3HtKp"]}],"impact":"serious","message":"Element has insufficient color contrast of 3.13 (foreground color: #ff00ff, background color: #ffffff, font size: 12.0pt (16px), font weight: normal). Expected contrast ratio of 4.5:1"}],"all":[],"none":[],"impact":"serious","html":"<p class=\"typography_body__uVgEN u-marginBottom-tiny u-marginTop-2\">or</p>","target":[".u-marginBottom-tiny"],"failureSummary":"Fix any of the following:\n  Element has insufficient color contrast of 3.13 (foreground color: #ff00ff, background color: #ffffff, font size: 12.0pt (16px), font weight: normal). Expected contrast ratio of 4.5:1"},{"any":[{"id":"color-contrast","data":{"fgColor":"#ff00ff","bgColor":"#ffffff","contrastRatio":3.13,"fontSize":"12.0pt (16px)","fontWeight":"normal","expectedContrastRatio":"4.5:1"},"relatedNodes":[{"html":"<body>","target":["body"]}],"impact":"serious","message":"Element has insufficient color contrast of 3.13 (foreground color: #ff00ff, background color: #ffffff, font size: 12.0pt (16px), font weight: normal). Expected contrast ratio of 4.5:1"}],"all":[],"none":[],"impact":"serious","html":"<p class=\"typography_body__uVgEN\">Next, your stylist will send a personalized preview of your first Trunk.</p>","target":[".Details_footer__lmhIs > .typography_body__uVgEN"],"failureSummary":"Fix any of the following:\n  Element has insufficient color contrast of 3.13 (foreground color: #ff00ff, background color: #ffffff, font size: 12.0pt (16px), font weight: normal). Expected contrast ratio of 4.5:1"}]}]},{"id":"20191205","route":{"id":"get-started_details","path":"/get-started/details"},"needsManualCheck":false,"violations":[{"id":"aria-input-field-name","impact":"serious","tags":["wcag2a","wcag412"],"description":"Ensures every ARIA input field has an accessible name","help":"ARIA input fields have an accessible name","helpUrl":"https://dequeuniversity.com/rules/axe/3.3/aria-input-field-name?application=axe-puppeteer","nodes":[{"any":[{"id":"aria-label","data":null,"relatedNodes":[],"impact":"serious","message":"aria-label attribute does not exist or is empty"},{"id":"aria-labelledby","data":null,"relatedNodes":[],"impact":"serious","message":"aria-labelledby attribute does not exist, references elements that do not exist or references elements that are empty"},{"id":"non-empty-title","data":null,"relatedNodes":[],"impact":"serious","message":"Element has no title attribute or the title attribute is empty"}],"all":[],"none":[],"impact":"serious","html":"<div tabindex=\"0\" class=\"SomethingElse_main__16if9\" data-testid=\"something-else\" role=\"combobox\" aria-expanded=\"false\" aria-haspopup=\"listbox\" aria-labelledby=\"downshift-0-label\">","target":["div[aria-labelledby=\"downshift-0-label\"]"],"failureSummary":"Fix any of the following:\n  aria-label attribute does not exist or is empty\n  aria-labelledby attribute does not exist, references elements that do not exist or references elements that are empty\n  Element has no title attribute or the title attribute is empty"},{"any":[{"id":"aria-label","data":null,"relatedNodes":[],"impact":"serious","message":"aria-label attribute does not exist or is empty"},{"id":"aria-labelledby","data":null,"relatedNodes":[],"impact":"serious","message":"aria-labelledby attribute does not exist, references elements that do not exist or references elements that are empty"},{"id":"non-empty-title","data":null,"relatedNodes":[],"impact":"serious","message":"Element has no title attribute or the title attribute is empty"}],"all":[],"none":[],"impact":"serious","html":"<div tabindex=\"0\" class=\"SomethingElse_main__16if9\" data-testid=\"something-else\" role=\"combobox\" aria-expanded=\"false\" aria-haspopup=\"listbox\" aria-labelledby=\"downshift-1-label\">","target":["div[aria-labelledby=\"downshift-1-label\"]"],"failureSummary":"Fix any of the following:\n  aria-label attribute does not exist or is empty\n  aria-labelledby attribute does not exist, references elements that do not exist or references elements that are empty\n  Element has no title attribute or the title attribute is empty"}]},{"id":"aria-required-children","impact":"critical","tags":["cat.aria","wcag2a","wcag131"],"description":"Ensures elements with an ARIA role that require child roles contain them","help":"Certain ARIA roles must contain particular children","helpUrl":"https://dequeuniversity.com/rules/axe/3.3/aria-required-children?application=axe-puppeteer","nodes":[{"any":[{"id":"aria-required-children","data":["textbox"],"relatedNodes":[],"impact":"critical","message":"Required ARIA child role not present: textbox"}],"all":[],"none":[],"impact":"critical","html":"<div tabindex=\"0\" class=\"SomethingElse_main__16if9\" data-testid=\"something-else\" role=\"combobox\" aria-expanded=\"false\" aria-haspopup=\"listbox\" aria-labelledby=\"downshift-0-label\">","target":["div[aria-labelledby=\"downshift-0-label\"]"],"failureSummary":"Fix any of the following:\n  Required ARIA child role not present: textbox"},{"any":[{"id":"aria-required-children","data":["textbox"],"relatedNodes":[],"impact":"critical","message":"Required ARIA child role not present: textbox"}],"all":[],"none":[],"impact":"critical","html":"<div tabindex=\"0\" class=\"SomethingElse_main__16if9\" data-testid=\"something-else\" role=\"combobox\" aria-expanded=\"false\" aria-haspopup=\"listbox\" aria-labelledby=\"downshift-1-label\">","target":["div[aria-labelledby=\"downshift-1-label\"]"],"failureSummary":"Fix any of the following:\n  Required ARIA child role not present: textbox"}]},{"id":"aria-valid-attr-value","impact":"critical","tags":["cat.aria","wcag2a","wcag412"],"description":"Ensures all ARIA attributes have valid values","help":"ARIA attributes must conform to valid values","helpUrl":"https://dequeuniversity.com/rules/axe/3.3/aria-valid-attr-value?application=axe-puppeteer","nodes":[{"any":[],"all":[{"id":"aria-valid-attr-value","data":["aria-labelledby=\"downshift-0-label\""],"relatedNodes":[],"impact":"critical","message":"Invalid ARIA attribute value: aria-labelledby=\"downshift-0-label\""}],"none":[],"impact":"critical","html":"<div tabindex=\"0\" class=\"SomethingElse_main__16if9\" data-testid=\"something-else\" role=\"combobox\" aria-expanded=\"false\" aria-haspopup=\"listbox\" aria-labelledby=\"downshift-0-label\">","target":["div[aria-labelledby=\"downshift-0-label\"]"],"failureSummary":"Fix all of the following:\n  Invalid ARIA attribute value: aria-labelledby=\"downshift-0-label\""},{"any":[],"all":[{"id":"aria-valid-attr-value","data":["aria-labelledby=\"downshift-1-label\""],"relatedNodes":[],"impact":"critical","message":"Invalid ARIA attribute value: aria-labelledby=\"downshift-1-label\""}],"none":[],"impact":"critical","html":"<div tabindex=\"0\" class=\"SomethingElse_main__16if9\" data-testid=\"something-else\" role=\"combobox\" aria-expanded=\"false\" aria-haspopup=\"listbox\" aria-labelledby=\"downshift-1-label\">","target":["div[aria-labelledby=\"downshift-1-label\"]"],"failureSummary":"Fix all of the following:\n  Invalid ARIA attribute value: aria-labelledby=\"downshift-1-label\""}]}]},{"id":"20191209","route":{"id":"get-started_details","path":"/get-started/details"},"needsManualCheck":false,"violations":[{"id":"aria-input-field-name","impact":"serious","tags":["wcag2a","wcag412"],"description":"Ensures every ARIA input field has an accessible name","help":"ARIA input fields have an accessible name","helpUrl":"https://dequeuniversity.com/rules/axe/3.3/aria-input-field-name?application=axe-puppeteer","nodes":[{"any":[{"id":"aria-label","data":null,"relatedNodes":[],"impact":"serious","message":"aria-label attribute does not exist or is empty"},{"id":"aria-labelledby","data":null,"relatedNodes":[],"impact":"serious","message":"aria-labelledby attribute does not exist, references elements that do not exist or references elements that are empty"},{"id":"non-empty-title","data":null,"relatedNodes":[],"impact":"serious","message":"Element has no title attribute or the title attribute is empty"}],"all":[],"none":[],"impact":"serious","html":"<div tabindex=\"0\" class=\"SomethingElse_main__16if9\" data-testid=\"something-else\" role=\"combobox\" aria-expanded=\"false\" aria-haspopup=\"listbox\" aria-labelledby=\"downshift-0-label\">","target":["div[aria-labelledby=\"downshift-0-label\"]"],"failureSummary":"Fix any of the following:\n  aria-label attribute does not exist or is empty\n  aria-labelledby attribute does not exist, references elements that do not exist or references elements that are empty\n  Element has no title attribute or the title attribute is empty"},{"any":[{"id":"aria-label","data":null,"relatedNodes":[],"impact":"serious","message":"aria-label attribute does not exist or is empty"},{"id":"aria-labelledby","data":null,"relatedNodes":[],"impact":"serious","message":"aria-labelledby attribute does not exist, references elements that do not exist or references elements that are empty"},{"id":"non-empty-title","data":null,"relatedNodes":[],"impact":"serious","message":"Element has no title attribute or the title attribute is empty"}],"all":[],"none":[],"impact":"serious","html":"<div tabindex=\"0\" class=\"SomethingElse_main__16if9\" data-testid=\"something-else\" role=\"combobox\" aria-expanded=\"false\" aria-haspopup=\"listbox\" aria-labelledby=\"downshift-1-label\">","target":["div[aria-labelledby=\"downshift-1-label\"]"],"failureSummary":"Fix any of the following:\n  aria-label attribute does not exist or is empty\n  aria-labelledby attribute does not exist, references elements that do not exist or references elements that are empty\n  Element has no title attribute or the title attribute is empty"}]},{"id":"aria-required-children","impact":"critical","tags":["cat.aria","wcag2a","wcag131"],"description":"Ensures elements with an ARIA role that require child roles contain them","help":"Certain ARIA roles must contain particular children","helpUrl":"https://dequeuniversity.com/rules/axe/3.3/aria-required-children?application=axe-puppeteer","nodes":[{"any":[{"id":"aria-required-children","data":["textbox"],"relatedNodes":[],"impact":"critical","message":"Required ARIA child role not present: textbox"}],"all":[],"none":[],"impact":"critical","html":"<div tabindex=\"0\" class=\"SomethingElse_main__16if9\" data-testid=\"something-else\" role=\"combobox\" aria-expanded=\"false\" aria-haspopup=\"listbox\" aria-labelledby=\"downshift-0-label\">","target":["div[aria-labelledby=\"downshift-0-label\"]"],"failureSummary":"Fix any of the following:\n  Required ARIA child role not present: textbox"},{"any":[{"id":"aria-required-children","data":["textbox"],"relatedNodes":[],"impact":"critical","message":"Required ARIA child role not present: textbox"}],"all":[],"none":[],"impact":"critical","html":"<div tabindex=\"0\" class=\"SomethingElse_main__16if9\" data-testid=\"something-else\" role=\"combobox\" aria-expanded=\"false\" aria-haspopup=\"listbox\" aria-labelledby=\"downshift-1-label\">","target":["div[aria-labelledby=\"downshift-1-label\"]"],"failureSummary":"Fix any of the following:\n  Required ARIA child role not present: textbox"}]},{"id":"aria-valid-attr-value","impact":"critical","tags":["cat.aria","wcag2a","wcag412"],"description":"Ensures all ARIA attributes have valid values","help":"ARIA attributes must conform to valid values","helpUrl":"https://dequeuniversity.com/rules/axe/3.3/aria-valid-attr-value?application=axe-puppeteer","nodes":[{"any":[],"all":[{"id":"aria-valid-attr-value","data":["aria-labelledby=\"downshift-0-label\""],"relatedNodes":[],"impact":"critical","message":"Invalid ARIA attribute value: aria-labelledby=\"downshift-0-label\""}],"none":[],"impact":"critical","html":"<div tabindex=\"0\" class=\"SomethingElse_main__16if9\" data-testid=\"something-else\" role=\"combobox\" aria-expanded=\"false\" aria-haspopup=\"listbox\" aria-labelledby=\"downshift-0-label\">","target":["div[aria-labelledby=\"downshift-0-label\"]"],"failureSummary":"Fix all of the following:\n  Invalid ARIA attribute value: aria-labelledby=\"downshift-0-label\""},{"any":[],"all":[{"id":"aria-valid-attr-value","data":["aria-labelledby=\"downshift-1-label\""],"relatedNodes":[],"impact":"critical","message":"Invalid ARIA attribute value: aria-labelledby=\"downshift-1-label\""}],"none":[],"impact":"critical","html":"<div tabindex=\"0\" class=\"SomethingElse_main__16if9\" data-testid=\"something-else\" role=\"combobox\" aria-expanded=\"false\" aria-haspopup=\"listbox\" aria-labelledby=\"downshift-1-label\">","target":["div[aria-labelledby=\"downshift-1-label\"]"],"failureSummary":"Fix all of the following:\n  Invalid ARIA attribute value: aria-labelledby=\"downshift-1-label\""}]}]},{"id":"20191212","route":{"id":"get-started_details","path":"/get-started/details"},"needsManualCheck":false,"violations":[{"id":"aria-input-field-name","impact":"serious","tags":["wcag2a","wcag412"],"description":"Ensures every ARIA input field has an accessible name","help":"ARIA input fields have an accessible name","helpUrl":"https://dequeuniversity.com/rules/axe/3.3/aria-input-field-name?application=axe-puppeteer","nodes":[{"any":[{"id":"aria-label","data":null,"relatedNodes":[],"impact":"serious","message":"aria-label attribute does not exist or is empty"},{"id":"aria-labelledby","data":null,"relatedNodes":[],"impact":"serious","message":"aria-labelledby attribute does not exist, references elements that do not exist or references elements that are empty"},{"id":"non-empty-title","data":null,"relatedNodes":[],"impact":"serious","message":"Element has no title attribute or the title attribute is empty"}],"all":[],"none":[],"impact":"serious","html":"<div tabindex=\"0\" class=\"SomethingElse_main__16if9\" data-testid=\"something-else\" role=\"combobox\" aria-expanded=\"false\" aria-haspopup=\"listbox\" aria-labelledby=\"downshift-0-label\">","target":["div[aria-labelledby=\"downshift-0-label\"]"],"failureSummary":"Fix any of the following:\n  aria-label attribute does not exist or is empty\n  aria-labelledby attribute does not exist, references elements that do not exist or references elements that are empty\n  Element has no title attribute or the title attribute is empty"},{"any":[{"id":"aria-label","data":null,"relatedNodes":[],"impact":"serious","message":"aria-label attribute does not exist or is empty"},{"id":"aria-labelledby","data":null,"relatedNodes":[],"impact":"serious","message":"aria-labelledby attribute does not exist, references elements that do not exist or references elements that are empty"},{"id":"non-empty-title","data":null,"relatedNodes":[],"impact":"serious","message":"Element has no title attribute or the title attribute is empty"}],"all":[],"none":[],"impact":"serious","html":"<div tabindex=\"0\" class=\"SomethingElse_main__16if9\" data-testid=\"something-else\" role=\"combobox\" aria-expanded=\"false\" aria-haspopup=\"listbox\" aria-labelledby=\"downshift-1-label\">","target":["div[aria-labelledby=\"downshift-1-label\"]"],"failureSummary":"Fix any of the following:\n  aria-label attribute does not exist or is empty\n  aria-labelledby attribute does not exist, references elements that do not exist or references elements that are empty\n  Element has no title attribute or the title attribute is empty"}]},{"id":"aria-required-children","impact":"critical","tags":["cat.aria","wcag2a","wcag131"],"description":"Ensures elements with an ARIA role that require child roles contain them","help":"Certain ARIA roles must contain particular children","helpUrl":"https://dequeuniversity.com/rules/axe/3.3/aria-required-children?application=axe-puppeteer","nodes":[{"any":[{"id":"aria-required-children","data":["textbox"],"relatedNodes":[],"impact":"critical","message":"Required ARIA child role not present: textbox"}],"all":[],"none":[],"impact":"critical","html":"<div tabindex=\"0\" class=\"SomethingElse_main__16if9\" data-testid=\"something-else\" role=\"combobox\" aria-expanded=\"false\" aria-haspopup=\"listbox\" aria-labelledby=\"downshift-0-label\">","target":["div[aria-labelledby=\"downshift-0-label\"]"],"failureSummary":"Fix any of the following:\n  Required ARIA child role not present: textbox"},{"any":[{"id":"aria-required-children","data":["textbox"],"relatedNodes":[],"impact":"critical","message":"Required ARIA child role not present: textbox"}],"all":[],"none":[],"impact":"critical","html":"<div tabindex=\"0\" class=\"SomethingElse_main__16if9\" data-testid=\"something-else\" role=\"combobox\" aria-expanded=\"false\" aria-haspopup=\"listbox\" aria-labelledby=\"downshift-1-label\">","target":["div[aria-labelledby=\"downshift-1-label\"]"],"failureSummary":"Fix any of the following:\n  Required ARIA child role not present: textbox"}]},{"id":"aria-valid-attr-value","impact":"critical","tags":["cat.aria","wcag2a","wcag412"],"description":"Ensures all ARIA attributes have valid values","help":"ARIA attributes must conform to valid values","helpUrl":"https://dequeuniversity.com/rules/axe/3.3/aria-valid-attr-value?application=axe-puppeteer","nodes":[{"any":[],"all":[{"id":"aria-valid-attr-value","data":["aria-labelledby=\"downshift-0-label\""],"relatedNodes":[],"impact":"critical","message":"Invalid ARIA attribute value: aria-labelledby=\"downshift-0-label\""}],"none":[],"impact":"critical","html":"<div tabindex=\"0\" class=\"SomethingElse_main__16if9\" data-testid=\"something-else\" role=\"combobox\" aria-expanded=\"false\" aria-haspopup=\"listbox\" aria-labelledby=\"downshift-0-label\">","target":["div[aria-labelledby=\"downshift-0-label\"]"],"failureSummary":"Fix all of the following:\n  Invalid ARIA attribute value: aria-labelledby=\"downshift-0-label\""},{"any":[],"all":[{"id":"aria-valid-attr-value","data":["aria-labelledby=\"downshift-1-label\""],"relatedNodes":[],"impact":"critical","message":"Invalid ARIA attribute value: aria-labelledby=\"downshift-1-label\""}],"none":[],"impact":"critical","html":"<div tabindex=\"0\" class=\"SomethingElse_main__16if9\" data-testid=\"something-else\" role=\"combobox\" aria-expanded=\"false\" aria-haspopup=\"listbox\" aria-labelledby=\"downshift-1-label\">","target":["div[aria-labelledby=\"downshift-1-label\"]"],"failureSummary":"Fix all of the following:\n  Invalid ARIA attribute value: aria-labelledby=\"downshift-1-label\""}]}]},{"id":"20191213","route":{"id":"get-started_details","path":"/get-started/details"},"needsManualCheck":false,"violations":[]},{"id":"20191218","route":{"id":"get-started_details","path":"/get-started/details"},"needsManualCheck":false,"violations":[]},{"id":"20200103","route":{"id":"get-started_details","path":"/get-started/details"},"needsManualCheck":false,"violations":[]},{"id":"20200108--pre-typescript","route":{"id":"get-started_details","path":"/get-started/details"},"needsManualCheck":false,"violations":[]},{"id":"20200108","route":{"id":"get-started_details","path":"/get-started/details"},"needsManualCheck":false,"violations":[]},{"id":"20200116","route":{"id":"get-started_details","path":"/get-started/details"},"needsManualCheck":false,"violations":[]},{"id":"20200123","route":{"id":"get-started_details","path":"/get-started/details"},"needsManualCheck":false,"violations":[]},{"id":"20200130","route":{"id":"get-started_details","path":"/get-started/details"},"needsManualCheck":false,"violations":[]}]